{"commitInfo":{"timestamp":1708274562490,"operation":"WRITE","operationParameters":{"mode":"Overwrite","partitionBy":"[]"},"readVersion":36,"isolationLevel":"Serializable","isBlindAppend":false,"operationMetrics":{"numFiles":"1","numOutputRows":"242","numOutputBytes":"4551"},"engineInfo":"Apache-Spark/3.5.0 Delta-Lake/3.0.0","txnId":"4290c41c-116b-46f0-ae7d-f04fe35413da"}}
{"add":{"path":"part-00000-62f36cf4-1db7-457d-b764-363ebc4fec34-c000.snappy.parquet","partitionValues":{},"size":4551,"modificationTime":1708274562301,"dataChange":true,"stats":"{\"numRecords\":242,\"minValues\":{\"size\":\"BIG\",\"day\":2,\"month\":1,\"year\":2024,\"totalunitsold\":1,\"totalrevenue\":54},\"maxValues\":{\"size\":\"VERY BIG\",\"day\":31,\"month\":2,\"year\":2024,\"totalunitsold\":5381,\"totalrevenue\":194857},\"nullCount\":{\"size\":0,\"day\":0,\"month\":0,\"year\":0,\"totalunitsold\":0,\"totalrevenue\":0}}"}}
{"remove":{"path":"part-00000-55853ca6-cf91-4bf8-bf37-3a702f7b2c60-c000.snappy.parquet","deletionTimestamp":1708274562489,"dataChange":true,"extendedFileMetadata":true,"partitionValues":{},"size":4449}}
