{"commitInfo":{"timestamp":1708101535965,"operation":"WRITE","operationParameters":{"mode":"Overwrite","partitionBy":"[]"},"readVersion":32,"isolationLevel":"Serializable","isBlindAppend":false,"operationMetrics":{"numFiles":"1","numOutputRows":"20","numOutputBytes":"1926"},"engineInfo":"Apache-Spark/3.5.0 Delta-Lake/3.0.0","txnId":"e67c1526-bf6a-45f2-a475-13b2e3e23781"}}
{"add":{"path":"part-00000-9d1fadd6-4aaa-46ec-8137-49cee11a56c7-c000.snappy.parquet","partitionValues":{},"size":1926,"modificationTime":1708101534601,"dataChange":true,"stats":"{\"numRecords\":20,\"minValues\":{\"size\":\"BIG\",\"month\":1,\"year\":2024,\"totalunitsold\":24,\"totalrevenue\":1296},\"maxValues\":{\"size\":\"VERY BIG\",\"month\":2,\"year\":2024,\"totalunitsold\":31648,\"totalrevenue\":1175589},\"nullCount\":{\"size\":0,\"month\":0,\"year\":0,\"totalunitsold\":0,\"totalrevenue\":0}}"}}
{"remove":{"path":"part-00000-306762d2-b6a3-4630-8694-09520c11b2a0-c000.snappy.parquet","deletionTimestamp":1708101535964,"dataChange":true,"extendedFileMetadata":true,"partitionValues":{},"size":1926}}
