{"commitInfo":{"timestamp":1706064520227,"operation":"WRITE","operationParameters":{"mode":"Overwrite","partitionBy":"[]"},"isolationLevel":"Serializable","isBlindAppend":false,"operationMetrics":{"numFiles":"1","numOutputRows":"0","numOutputBytes":"1227"},"engineInfo":"Apache-Spark/3.5.0 Delta-Lake/3.0.0","txnId":"c548f7c4-2cdd-4f11-aed8-afa55e3a4595"}}
{"metaData":{"id":"a0330c54-1d08-4e9a-b0d6-6713fcfc2706","format":{"provider":"parquet","options":{}},"schemaString":"{\"type\":\"struct\",\"fields\":[{\"name\":\"jellycatname\",\"type\":\"string\",\"nullable\":true,\"metadata\":{\"scale\":0}},{\"name\":\"size\",\"type\":\"string\",\"nullable\":true,\"metadata\":{\"scale\":0}},{\"name\":\"stocktoday\",\"type\":\"string\",\"nullable\":true,\"metadata\":{\"scale\":0}},{\"name\":\"category\",\"type\":\"string\",\"nullable\":true,\"metadata\":{\"scale\":0}},{\"name\":\"stock3daysago\",\"type\":\"string\",\"nullable\":true,\"metadata\":{\"scale\":0}},{\"name\":\"link\",\"type\":\"string\",\"nullable\":true,\"metadata\":{\"scale\":0}},{\"name\":\"imagelink\",\"type\":\"string\",\"nullable\":true,\"metadata\":{\"scale\":0}},{\"name\":\"price\",\"type\":\"decimal(10,0)\",\"nullable\":true,\"metadata\":{}},{\"name\":\"height\",\"type\":\"decimal(10,0)\",\"nullable\":true,\"metadata\":{}},{\"name\":\"width\",\"type\":\"decimal(10,0)\",\"nullable\":true,\"metadata\":{}}]}","partitionColumns":[],"configuration":{},"createdTime":1706064518507}}
{"protocol":{"minReaderVersion":1,"minWriterVersion":2}}
